{
  "abborre": "meat and fish",
  "agar agar": "pantry",
  "almond": "pantry",
  "almond flour": "pantry",
  "almonds": "pantry",
  "ananas": "fruit & vegetables",
  "anchovies": "meat and fish",
  "anchovy": "meat and fish",
  "anka": "meat and fish",
  "ansjovis": "meat and fish",
  "apelsin": "fruit & vegetables",
  "apelsiner": "fruit & vegetables",
  "apple": "fruit & vegetables",
  "apple cider vinegar": "pantry",
  "apples": "fruit & vegetables",
  "apricot": "fruit & vegetables",
  "apricots": "fruit & vegetables",
  "aprikos": "fruit & vegetables",
  "aprikoser": "fruit & vegetables",
  "arborio rice": "pantry",
  "artichoke": "fruit & vegetables",
  "artichokes": "fruit & vegetables",
  "arugula": "fruit & vegetables",
  "asparagus": "fruit & vegetables",
  "aubergine": "fruit & vegetables",
  "auberginer": "fruit & vegetables",
  "avocado": "fruit & vegetables",
  "avocados": "fruit & vegetables",
  "avokado": "fruit & vegetables",
  "bacon": "meat and fish",
  "bagel": "pantry",
  "bagels": "pantry",
  "baking powder": "pantry",
  "baking soda": "pantry",
  "bakpulver": "pantry",
  "balsamic vinegar": "pantry",
  "balsamvinäger": "pantry",
  "bamboo shoots": "fruit & vegetables",
  "bambuskott": "fruit & vegetables",
  "banan": "fruit & vegetables",
  "banana": "fruit & vegetables",
  "bananas": "fruit & vegetables",
  "bananer": "fruit & vegetables",
  "barbecue sauce": "pantry",
  "basil": "fruit & vegetables",
  "basilika": "fruit & vegetables",
  "basmati rice": "pantry",
  "basmatiris": "pantry",
  "bay leaf": "pantry",
  "bay leaves": "pantry",
  "bbq sauce": "pantry",
  "bean": "pantry",
  "bean sprouts": "fruit & vegetables",
  "beans": "pantry",
  "bechamel sauce": "pantry",
  "beef": "meat and fish",
  "beef broth": "pantry",
  "beef stock": "pantry",
  "beet": "fruit & vegetables",
  "beetroot": "fruit & vegetables",
  "beets": "fruit & vegetables",
  "bell pepper": "fruit & vegetables",
  "bell peppers": "fruit & vegetables",
  "biff": "meat and fish",
  "biffar": "meat and fish",
  "bikarbonat": "pantry",
  "biscuits": "pantry",
  "björnbär": "fruit & vegetables",
  "black beans": "pantry",
  "black pepper": "pantry",
  "black tea": "pantry",
  "blackberries": "fruit & vegetables",
  "blackberry": "fruit & vegetables",
  "blandfärs": "meat and fish",
  "blomkål": "fruit & vegetables",
  "blue cheese": "dairy",
  "blueberries": "fruit & vegetables",
  "blueberry": "fruit & vegetables",
  "bläckfisk": "meat and fish",
  "blåbär": "fruit & vegetables",
  "bok choy": "fruit & vegetables",
  "bouillon": "pantry",
  "bouillon cube": "pantry",
  "bouillon cubes": "pantry",
  "bratwurst": "meat and fish",
  "bread": "pantry",
  "breadcrumbs": "pantry",
  "bresaola": "meat and fish",
  "brie": "dairy",
  "brioche": "pantry",
  "broccoli": "fruit & vegetables",
  "broth": "pantry",
  "broths": "pantry",
  "brown gravy": "pantry",
  "brown sugar": "pantry",
  "brunsås": "pantry",
  "brussels sprouts": "fruit & vegetables",
  "brysselkål": "fruit & vegetables",
  "bröd": "pantry",
  "bulgur": "pantry",
  "buljong": "pantry",
  "buljonger": "pantry",
  "buljongtärning": "pantry",
  "buljongtärningar": "pantry",
  "butter": "dairy",
  "béchamel sauce": "pantry",
  "böna": "pantry",
  "böngroddar": "fruit & vegetables",
  "bönor": "pantry",
  "cabbage": "fruit & vegetables",
  "calamari": "meat and fish",
  "camembert": "dairy",
  "canned tomatoes": "pantry",
  "canola oil": "pantry",
  "cantaloupe": "fruit & vegetables",
  "capers": "pantry",
  "cardamom": "pantry",
  "carrot": "fruit & vegetables",
  "carrots": "fruit & vegetables",
  "cashew": "pantry",
  "cashewnöt": "pantry",
  "cashewnötter": "pantry",
  "cashews": "pantry",
  "cauliflower": "fruit & vegetables",
  "cayenne": "pantry",
  "cayennepeppar": "pantry",
  "celeriac": "fruit & vegetables",
  "celery": "fruit & vegetables",
  "cereal": "pantry",
  "champignon": "fruit & vegetables",
  "champignons": "fruit & vegetables",
  "champinjon": "fruit & vegetables",
  "champinjoner": "fruit & vegetables",
  "chanterelle": "fruit & vegetables",
  "chanterelles": "fruit & vegetables",
  "char": "meat and fish",
  "cheddar": "dairy",
  "cheese": "dairy",
  "cheeses": "dairy",
  "cherries": "fruit & vegetables",
  "cherry": "fruit & vegetables",
  "chevre": "dairy",
  "chia seeds": "pantry",
  "chiafrön": "pantry",
  "chicken": "meat and fish",
  "chicken breast": "meat and fish",
  "chicken broth": "pantry",
  "chicken drumsticks": "meat and fish",
  "chicken stock": "pantry",
  "chicken thigh": "meat and fish",
  "chicken wings": "meat and fish",
  "chickens": "meat and fish",
  "chickpea": "pantry",
  "chickpeas": "pantry",
  "chili": "fruit & vegetables",
  "chili flakes": "pantry",
  "chili pepper": "fruit & vegetables",
  "chili peppers": "fruit & vegetables",
  "chili sauce": "pantry",
  "chiliflakes": "pantry",
  "chilis": "fruit & vegetables",
  "chips": "pantry",
  "chives": "fruit & vegetables",
  "chocolate": "pantry",
  "choklad": "pantry",
  "chokladkräm": "pantry",
  "chorizo": "meat and fish",
  "chèvre": "dairy",
  "cilantro": "fruit & vegetables",
  "cinnamon": "pantry",
  "citron": "fruit & vegetables",
  "citroner": "fruit & vegetables",
  "citrongräs": "fruit & vegetables",
  "clementine": "fruit & vegetables",
  "clementines": "fruit & vegetables",
  "cloudberries": "fruit & vegetables",
  "cloudberry": "fruit & vegetables",
  "clove": "pantry",
  "cloves": "pantry",
  "cocoa": "pantry",
  "coconut cream": "pantry",
  "coconut milk": "pantry",
  "cod": "meat and fish",
  "coffee": "pantry",
  "cookies": "pantry",
  "cooking cream": "dairy",
  "coriander": "fruit & vegetables",
  "coriander seed": "pantry",
  "corn": "fruit & vegetables",
  "corn flour": "pantry",
  "cornstarch": "pantry",
  "cottage cheese": "dairy",
  "courgette": "fruit & vegetables",
  "couscous": "pantry",
  "crab": "meat and fish",
  "crab sticks": "meat and fish",
  "crabs": "meat and fish",
  "cracker": "pantry",
  "crackers": "pantry",
  "cranberries": "fruit & vegetables",
  "cranberry": "fruit & vegetables",
  "crayfish": "meat and fish",
  "cream": "dairy",
  "cream cheese": "dairy",
  "creme fraiche": "dairy",
  "crispbread": "pantry",
  "crisps": "pantry",
  "croissant": "pantry",
  "croissants": "pantry",
  "crushed tomatoes": "pantry",
  "crème fraîche": "dairy",
  "cucumber": "fruit & vegetables",
  "cucumbers": "fruit & vegetables",
  "cumin": "pantry",
  "curry paste": "pantry",
  "curry powder": "pantry",
  "dadel": "fruit & vegetables",
  "dadlar": "fruit & vegetables",
  "daikon": "fruit & vegetables",
  "dark chocolate": "pantry",
  "dark soy sauce": "pantry",
  "date": "fruit & vegetables",
  "dates": "fruit & vegetables",
  "demi glace": "pantry",
  "demiglace": "pantry",
  "dijon mustard": "pantry",
  "dill": "fruit & vegetables",
  "doenjang": "pantry",
  "doubanjiang": "pantry",
  "dried basil": "pantry",
  "dried oregano": "pantry",
  "dried rosemary": "pantry",
  "dried thyme": "pantry",
  "dry yeast": "pantry",
  "duck": "meat and fish",
  "dumpling wrappers": "pantry",
  "edam": "dairy",
  "edamame": "fruit & vegetables",
  "egg": "dairy",
  "egg noodle": "pantry",
  "egg noodles": "pantry",
  "egg white": "dairy",
  "egg whites": "dairy",
  "egg yolk": "dairy",
  "egg yolks": "dairy",
  "eggplant": "fruit & vegetables",
  "eggs": "dairy",
  "emmental": "dairy",
  "entrecote": "meat and fish",
  "entrecôte": "meat and fish",
  "falukorv": "meat and fish",
  "farfalle": "pantry",
  "farinsocker": "pantry",
  "fennel": "fruit & vegetables",
  "feta": "dairy",
  "fettuccine": "pantry",
  "fig": "fruit & vegetables",
  "figs": "fruit & vegetables",
  "fikon": "fruit & vegetables",
  "fil": "dairy",
  "filmjölk": "dairy",
  "fish": "meat and fish",
  "fish broth": "pantry",
  "fish fingers": "meat and fish",
  "fish sauce": "pantry",
  "fish stock": "pantry",
  "fisk": "meat and fish",
  "fiskbuljong": "pantry",
  "fiskfond": "pantry",
  "fiskpinnar": "meat and fish",
  "five spice": "pantry",
  "flank steak": "meat and fish",
  "flankstek": "meat and fish",
  "flingor": "pantry",
  "florsocker": "pantry",
  "flour": "pantry",
  "fläskkotlett": "meat and fish",
  "fläskkotletter": "meat and fish",
  "fläskkött": "meat and fish",
  "fond": "pantry",
  "fonder": "pantry",
  "fullkornsbröd": "pantry",
  "fusilli": "pantry",
  "fänkål": "fruit & vegetables",
  "färskost": "dairy",
  "galangal": "fruit & vegetables",
  "garam masala": "pantry",
  "garlic": "fruit & vegetables",
  "gelatin": "pantry",
  "gelatinblad": "pantry",
  "gelatine": "pantry",
  "getost": "dairy",
  "ginger": "fruit & vegetables",
  "ginger powder": "pantry",
  "glasnudlar": "pantry",
  "glass": "dairy",
  "glass noodles": "pantry",
  "gnocchi": "pantry",
  "goat cheese": "dairy",
  "gochujang": "pantry",
  "goose": "meat and fish",
  "gorgonzola": "dairy",
  "gouda": "dairy",
  "granatäpple": "fruit & vegetables",
  "granola": "pantry",
  "grape": "fruit & vegetables",
  "grapefruit": "fruit & vegetables",
  "grapefrukt": "fruit & vegetables",
  "grapes": "fruit & vegetables",
  "gravad lax": "meat and fish",
  "gravlax": "meat and fish",
  "gravy mix": "pantry",
  "greek yogurt": "dairy",
  "green beans": "fruit & vegetables",
  "green curry paste": "pantry",
  "green lentils": "pantry",
  "green peas": "fruit & vegetables",
  "green pesto": "pantry",
  "green tea": "pantry",
  "grekisk yoghurt": "dairy",
  "ground beef": "meat and fish",
  "gruyere": "dairy",
  "gruyère": "dairy",
  "grädde": "dairy",
  "gräddfil": "dairy",
  "gräslök": "fruit & vegetables",
  "gröna linser": "pantry",
  "gröna ärtor": "fruit & vegetables",
  "grönkål": "fruit & vegetables",
  "grönsaksbuljong": "pantry",
  "grönsaksfond": "pantry",
  "grönt te": "pantry",
  "guanciale": "meat and fish",
  "gul lök": "fruit & vegetables",
  "gula lökar": "fruit & vegetables",
  "gula ärtor": "pantry",
  "gurka": "fruit & vegetables",
  "gurkmeja": "pantry",
  "gurkor": "fruit & vegetables",
  "gädda": "meat and fish",
  "gås": "meat and fish",
  "gös": "meat and fish",
  "haddock": "meat and fish",
  "halibut": "meat and fish",
  "hallon": "fruit & vegetables",
  "halloumi": "dairy",
  "ham": "meat and fish",
  "hard cheese": "dairy",
  "haricots verts": "fruit & vegetables",
  "havre": "pantry",
  "havregryn": "pantry",
  "havssalt": "pantry",
  "hazelnut spread": "pantry",
  "heavy cream": "dairy",
  "herring": "meat and fish",
  "hjortron": "fruit & vegetables",
  "hoisin sauce": "pantry",
  "honey": "pantry",
  "honeydew melon": "fruit & vegetables",
  "honung": "pantry",
  "hot dog": "meat and fish",
  "hot dogs": "meat and fish",
  "hot sauce": "pantry",
  "hummer": "meat and fish",
  "hälleflundra": "meat and fish",
  "hårdost": "dairy",
  "högrev": "meat and fish",
  "ice cream": "dairy",
  "iceberg lettuce": "fruit & vegetables",
  "ingefära": "fruit & vegetables",
  "isbergssallad": "fruit & vegetables",
  "jalapeno": "fruit & vegetables",
  "jalapenos": "fruit & vegetables",
  "jalapeño": "fruit & vegetables",
  "jalapeños": "fruit & vegetables",
  "jam": "pantry",
  "jasmine rice": "pantry",
  "jasminris": "pantry",
  "jordgubbar": "fruit & vegetables",
  "jordgubbe": "fruit & vegetables",
  "jordnöt": "pantry",
  "jordnötsolja": "pantry",
  "jordnötssmör": "pantry",
  "jordnötter": "pantry",
  "jäst": "pantry",
  "kaffe": "pantry",
  "kakao": "pantry",
  "kakor": "pantry",
  "kale": "fruit & vegetables",
  "kalkon": "meat and fish",
  "kalv": "meat and fish",
  "kanel": "pantry",
  "kantarell": "fruit & vegetables",
  "kantareller": "fruit & vegetables",
  "kapris": "pantry",
  "kardemumma": "pantry",
  "kefir": "dairy",
  "keso": "dairy",
  "ketchup": "pantry",
  "kex": "pantry",
  "kidney beans": "pantry",
  "kikärta": "pantry",
  "kikärtor": "pantry",
  "kimchi": "pantry",
  "kiwi": "fruit & vegetables",
  "kiwis": "fruit & vegetables",
  "klementin": "fruit & vegetables",
  "klementiner": "fruit & vegetables",
  "knäckebröd": "pantry",
  "kokosgrädde": "pantry",
  "kokosmjölk": "pantry",
  "kolja": "meat and fish",
  "kombu": "pantry",
  "koriander": "fruit & vegetables",
  "korianderfrö": "pantry",
  "korv": "meat and fish",
  "korvar": "meat and fish",
  "krabba": "meat and fish",
  "krabbor": "meat and fish",
  "krabbpinnar": "meat and fish",
  "kronärtskocka": "fruit & vegetables",
  "kronärtskockor": "fruit & vegetables",
  "krossade tomater": "pantry",
  "kräfta": "meat and fish",
  "kräftor": "meat and fish",
  "kyckling": "meat and fish",
  "kycklingar": "meat and fish",
  "kycklingbröst": "meat and fish",
  "kycklingbuljong": "pantry",
  "kycklingfond": "pantry",
  "kycklingklubbor": "meat and fish",
  "kycklinglår": "meat and fish",
  "kycklingvingar": "meat and fish",
  "kål": "fruit & vegetables",
  "kålrot": "fruit & vegetables",
  "körsbär": "fruit & vegetables",
  "kött": "meat and fish",
  "köttbuljong": "pantry",
  "köttbullar": "meat and fish",
  "köttbulle": "meat and fish",
  "köttfond": "pantry",
  "köttfärs": "meat and fish",
  "lagerblad": "pantry",
  "lamb": "meat and fish",
  "lamb chops": "meat and fish",
  "lamb mince": "meat and fish",
  "lamm": "meat and fish",
  "lammfärs": "meat and fish",
  "lammkotletter": "meat and fish",
  "lasagna sheets": "pantry",
  "lasagneplattor": "pantry",
  "lax": "meat and fish",
  "leek": "fruit & vegetables",
  "leeks": "fruit & vegetables",
  "lemon": "fruit & vegetables",
  "lemongrass": "fruit & vegetables",
  "lemons": "fruit & vegetables",
  "lentil": "pantry",
  "lentils": "pantry",
  "lettuce": "fruit & vegetables",
  "light soy sauce": "pantry",
  "lime": "fruit & vegetables",
  "limes": "fruit & vegetables",
  "lingon": "fruit & vegetables",
  "lingonberries": "fruit & vegetables",
  "lingonberry": "fruit & vegetables",
  "linguine": "pantry",
  "lins": "pantry",
  "linser": "pantry",
  "lobster": "meat and fish",
  "low fat milk": "dairy",
  "lättmjölk": "dairy",
  "lök": "fruit & vegetables",
  "lökar": "fruit & vegetables",
  "lönnsirap": "pantry",
  "macaroni": "pantry",
  "mackerel": "meat and fish",
  "maize": "fruit & vegetables",
  "maizena": "pantry",
  "majonnäs": "pantry",
  "majs": "fruit & vegetables",
  "majsmjöl": "pantry",
  "makaroner": "pantry",
  "makrill": "meat and fish",
  "malen ingefära": "pantry",
  "mandarin": "fruit & vegetables",
  "mandariner": "fruit & vegetables",
  "mandarins": "fruit & vegetables",
  "mandel": "pantry",
  "mandelmjöl": "pantry",
  "mango": "fruit & vegetables",
  "mangoes": "fruit & vegetables",
  "mangos": "fruit & vegetables",
  "mannagryn": "pantry",
  "maple syrup": "pantry",
  "marmalade": "pantry",
  "marmelad": "pantry",
  "mascarpone": "dairy",
  "matjes herring": "meat and fish",
  "matjessill": "meat and fish",
  "matlagningsgrädde": "dairy",
  "mayonnaise": "pantry",
  "meat": "meat and fish",
  "meatball": "meat and fish",
  "meatballs": "meat and fish",
  "melon": "fruit & vegetables",
  "melons": "fruit & vegetables",
  "milk": "dairy",
  "milk chocolate": "pantry",
  "minced meat": "meat and fish",
  "mint": "fruit & vegetables",
  "mirin": "pantry",
  "miso": "pantry",
  "miso paste": "pantry",
  "mjöl": "pantry",
  "mjölk": "dairy",
  "mjölkchoklad": "pantry",
  "moose meat": "meat and fish",
  "morot": "fruit & vegetables",
  "mortadella": "meat and fish",
  "morötter": "fruit & vegetables",
  "mozzarella": "dairy",
  "muesli": "pantry",
  "mushroom": "fruit & vegetables",
  "mushrooms": "fruit & vegetables",
  "muskot": "pantry",
  "mussel": "meat and fish",
  "mussels": "meat and fish",
  "mussla": "meat and fish",
  "musslor": "meat and fish",
  "mustard": "pantry",
  "mynta": "fruit & vegetables",
  "mörk choklad": "pantry",
  "müsli": "pantry",
  "naan": "pantry",
  "nachos": "pantry",
  "nectarine": "fruit & vegetables",
  "nectarines": "fruit & vegetables",
  "nejlika": "pantry",
  "nejlikor": "pantry",
  "nektarin": "fruit & vegetables",
  "nektariner": "fruit & vegetables",
  "noodle": "pantry",
  "noodles": "pantry",
  "nori": "pantry",
  "nudel": "pantry",
  "nudlar": "pantry",
  "nutmeg": "pantry",
  "nuts": "pantry",
  "nötfärs": "meat and fish",
  "nötkött": "meat and fish",
  "nötter": "pantry",
  "oatmeal": "pantry",
  "oats": "pantry",
  "octopus": "meat and fish",
  "oil": "pantry",
  "okra": "fruit & vegetables",
  "olive oil": "pantry",
  "oliver": "pantry",
  "olives": "pantry",
  "olivolja": "pantry",
  "olja": "pantry",
  "onion": "fruit & vegetables",
  "onions": "fruit & vegetables",
  "orange": "fruit & vegetables",
  "oranges": "fruit & vegetables",
  "oregano": "pantry",
  "ost": "dairy",
  "ostar": "dairy",
  "ostron": "meat and fish",
  "ostronskivling": "fruit & vegetables",
  "oxfilé": "meat and fish",
  "oyster": "meat and fish",
  "oyster mushroom": "fruit & vegetables",
  "oyster sauce": "pantry",
  "oysters": "meat and fish",
  "paella rice": "pantry",
  "paellaris": "pantry",
  "pak choi": "fruit & vegetables",
  "palsternacka": "fruit & vegetables",
  "palsternackor": "fruit & vegetables",
  "pancetta": "meat and fish",
  "paneer": "dairy",
  "panko": "pantry",
  "paprika": "fruit & vegetables",
  "paprika powder": "pantry",
  "paprikapulver": "pantry",
  "parma ham": "meat and fish",
  "parmesan": "dairy",
  "parmigiano reggiano": "dairy",
  "parsley": "fruit & vegetables",
  "parsnip": "fruit & vegetables",
  "parsnips": "fruit & vegetables",
  "passata": "pantry",
  "passion fruit": "fruit & vegetables",
  "passionsfrukt": "fruit & vegetables",
  "pasta": "pantry",
  "peach": "fruit & vegetables",
  "peaches": "fruit & vegetables",
  "peanut": "pantry",
  "peanut butter": "pantry",
  "peanut oil": "pantry",
  "peanuts": "pantry",
  "pear": "fruit & vegetables",
  "pears": "fruit & vegetables",
  "peas": "fruit & vegetables",
  "pecorino": "dairy",
  "penne": "pantry",
  "pepparkorn": "pantry",
  "peppercorns": "pantry",
  "pepperoni": "meat and fish",
  "perch": "meat and fish",
  "persika": "fruit & vegetables",
  "persikor": "fruit & vegetables",
  "persilja": "fruit & vegetables",
  "pesto": "pantry",
  "pickled cucumber": "pantry",
  "pickles": "pantry",
  "pike": "meat and fish",
  "pilgrimsmussla": "meat and fish",
  "pilgrimsmusslor": "meat and fish",
  "pine nut": "pantry",
  "pine nuts": "pantry",
  "pineapple": "fruit & vegetables",
  "pinjenöt": "pantry",
  "pinjenötter": "pantry",
  "pistachio": "pantry",
  "pistachios": "pantry",
  "pistasch": "pantry",
  "pita bread": "pantry",
  "pitabröd": "pantry",
  "pizza dough": "pantry",
  "pizza sauce": "pantry",
  "pizzadeg": "pantry",
  "pizzasås": "pantry",
  "plommon": "fruit & vegetables",
  "plum": "fruit & vegetables",
  "plums": "fruit & vegetables",
  "polenta": "pantry",
  "pollock": "meat and fish",
  "pomegranate": "fruit & vegetables",
  "popcorn": "pantry",
  "pork": "meat and fish",
  "pork belly": "meat and fish",
  "pork chop": "meat and fish",
  "pork chops": "meat and fish",
  "portobello": "fruit & vegetables",
  "potatis": "fruit & vegetables",
  "potatismjöl": "pantry",
  "potato": "fruit & vegetables",
  "potato chips": "pantry",
  "potato starch": "pantry",
  "potatoes": "fruit & vegetables",
  "powdered sugar": "pantry",
  "prawn": "meat and fish",
  "prawns": "meat and fish",
  "prinskorv": "meat and fish",
  "prosciutto": "meat and fish",
  "pulled pork": "meat and fish",
  "pumpafrön": "pantry",
  "pumpkin seeds": "pantry",
  "purjolök": "fruit & vegetables",
  "päron": "fruit & vegetables",
  "quinoa": "pantry",
  "raclette": "dairy",
  "radish": "fruit & vegetables",
  "radishes": "fruit & vegetables",
  "raisin": "fruit & vegetables",
  "raisins": "fruit & vegetables",
  "ramen": "pantry",
  "rapeseed oil": "pantry",
  "rapsolja": "pantry",
  "ras el hanout": "pantry",
  "raspberries": "fruit & vegetables",
  "raspberry": "fruit & vegetables",
  "ravioli": "pantry",
  "red cabbage": "fruit & vegetables",
  "red curry paste": "pantry",
  "red lentils": "pantry",
  "red onion": "fruit & vegetables",
  "red onions": "fruit & vegetables",
  "red pesto": "pantry",
  "reindeer meat": "meat and fish",
  "renkött": "meat and fish",
  "revben": "meat and fish",
  "ribeye": "meat and fish",
  "ribs": "meat and fish",
  "rice": "pantry",
  "rice noodles": "pantry",
  "rice paper": "pantry",
  "rice vinegar": "pantry",
  "ricotta": "dairy",
  "rigatoni": "pantry",
  "ris": "pantry",
  "risnudlar": "pantry",
  "risotto rice": "pantry",
  "rispapper": "pantry",
  "risvinäger": "pantry",
  "roast beef": "meat and fish",
  "rocket": "fruit & vegetables",
  "romaine lettuce": "fruit & vegetables",
  "romansallad": "fruit & vegetables",
  "rosemary": "fruit & vegetables",
  "rosmarin": "fruit & vegetables",
  "rotselleri": "fruit & vegetables",
  "roux": "pantry",
  "rova": "fruit & vegetables",
  "rovor": "fruit & vegetables",
  "ruccola": "fruit & vegetables",
  "russin": "fruit & vegetables",
  "rutabaga": "fruit & vegetables",
  "rye flour": "pantry",
  "rädisa": "fruit & vegetables",
  "rädisor": "fruit & vegetables",
  "räka": "meat and fish",
  "räkor": "meat and fish",
  "rågmjöl": "pantry",
  "röda linser": "pantry",
  "rödbeta": "fruit & vegetables",
  "rödbetor": "fruit & vegetables",
  "röding": "meat and fish",
  "rödkål": "fruit & vegetables",
  "rödlök": "fruit & vegetables",
  "rökt lax": "meat and fish",
  "rökt paprika": "pantry",
  "saffran": "pantry",
  "saffron": "pantry",
  "sage": "fruit & vegetables",
  "sake": "pantry",
  "salami": "meat and fish",
  "sallad": "fruit & vegetables",
  "salladslök": "fruit & vegetables",
  "salmon": "meat and fish",
  "salsa": "pantry",
  "salsiccia": "meat and fish",
  "salt": "pantry",
  "salted butter": "dairy",
  "salvia": "fruit & vegetables",
  "sardine": "meat and fish",
  "sardiner": "meat and fish",
  "sardines": "meat and fish",
  "sauerkraut": "pantry",
  "sausage": "meat and fish",
  "sausages": "meat and fish",
  "savoy cabbage": "fruit & vegetables",
  "savoykål": "fruit & vegetables",
  "scallop": "meat and fish",
  "scallops": "meat and fish",
  "schalottenlök": "fruit & vegetables",
  "sea bass": "meat and fish",
  "sea salt": "pantry",
  "seabass": "meat and fish",
  "seaweed": "fruit & vegetables",
  "sej": "meat and fish",
  "selleri": "fruit & vegetables",
  "semolina": "pantry",
  "senap": "pantry",
  "sesame oil": "pantry",
  "sesame seeds": "pantry",
  "sesamfrön": "pantry",
  "sesamolja": "pantry",
  "shallot": "fruit & vegetables",
  "shallots": "fruit & vegetables",
  "shaoxing wine": "pantry",
  "shiitake": "fruit & vegetables",
  "shrimp": "meat and fish",
  "shrimps": "meat and fish",
  "sidfläsk": "meat and fish",
  "sill": "meat and fish",
  "sirap": "pantry",
  "sirloin": "meat and fish",
  "sjögräs": "fruit & vegetables",
  "skim milk": "dairy",
  "skinka": "meat and fish",
  "skummjölk": "dairy",
  "smoked paprika": "pantry",
  "smoked salmon": "meat and fish",
  "smör": "dairy",
  "soba": "pantry",
  "socker": "pantry",
  "sockerärtor": "fruit & vegetables",
  "soja": "pantry",
  "sojabönor": "pantry",
  "solrosfrön": "pantry",
  "solrosolja": "pantry",
  "soltorkade tomater": "pantry",
  "sour cream": "dairy",
  "sourdough bread": "pantry",
  "soy sauce": "pantry",
  "soybeans": "pantry",
  "spaghetti": "pantry",
  "spare ribs": "meat and fish",
  "sparris": "fruit & vegetables",
  "spenat": "fruit & vegetables",
  "spinach": "fruit & vegetables",
  "spiskummin": "pantry",
  "spring onion": "fruit & vegetables",
  "spring onions": "fruit & vegetables",
  "spring roll wrappers": "pantry",
  "squash": "fruit & vegetables",
  "squid": "meat and fish",
  "sriracha": "pantry",
  "standardmjölk": "dairy",
  "steak": "meat and fish",
  "steaks": "meat and fish",
  "stock": "pantry",
  "stocks": "pantry",
  "strawberries": "fruit & vegetables",
  "strawberry": "fruit & vegetables",
  "ströbröd": "pantry",
  "sugar": "pantry",
  "sugar snap peas": "fruit & vegetables",
  "sumac": "pantry",
  "sun dried tomatoes": "pantry",
  "sunflower oil": "pantry",
  "sunflower seeds": "pantry",
  "surdegsbröd": "pantry",
  "surimi": "meat and fish",
  "surkål": "pantry",
  "sushi rice": "pantry",
  "svamp": "fruit & vegetables",
  "svart te": "pantry",
  "svarta bönor": "pantry",
  "svartpeppar": "pantry",
  "swede": "fruit & vegetables",
  "sweet chili sauce": "pantry",
  "sweet potato": "fruit & vegetables",
  "sweet potatoes": "fruit & vegetables",
  "sylt": "pantry",
  "syrup": "pantry",
  "sötpotatis": "fruit & vegetables",
  "tabasco": "pantry",
  "taco sauce": "pantry",
  "taco seasoning": "pantry",
  "taco shells": "pantry",
  "tacokrydda": "pantry",
  "tacoskal": "pantry",
  "tacosås": "pantry",
  "tagliatelle": "pantry",
  "tahini": "pantry",
  "tamari": "pantry",
  "te": "pantry",
  "tea": "pantry",
  "teriyaki sauce": "pantry",
  "thyme": "fruit & vegetables",
  "timjan": "fruit & vegetables",
  "tomat": "fruit & vegetables",
  "tomater": "fruit & vegetables",
  "tomato": "fruit & vegetables",
  "tomato paste": "pantry",
  "tomato sauce": "pantry",
  "tomatoes": "fruit & vegetables",
  "tomatpuré": "pantry",
  "tomatsås": "pantry",
  "tonfisk": "meat and fish",
  "torkad basilika": "pantry",
  "torkad oregano": "pantry",
  "torkad rosmarin": "pantry",
  "torkad timjan": "pantry",
  "torrjäst": "pantry",
  "torsk": "meat and fish",
  "tortellini": "pantry",
  "tortilla": "pantry",
  "tortilla chips": "pantry",
  "tortillas": "pantry",
  "tranbär": "fruit & vegetables",
  "trout": "meat and fish",
  "tuna": "meat and fish",
  "turkey": "meat and fish",
  "turkish yogurt": "dairy",
  "turkisk yoghurt": "dairy",
  "turmeric": "pantry",
  "turnip": "fruit & vegetables",
  "turnips": "fruit & vegetables",
  "udon": "pantry",
  "unsalted butter": "dairy",
  "valnöt": "pantry",
  "valnötter": "pantry",
  "vanilj": "pantry",
  "vaniljglass": "dairy",
  "vaniljsocker": "pantry",
  "vanilla": "pantry",
  "vanilla ice cream": "dairy",
  "vanilla sugar": "pantry",
  "varmkorv": "meat and fish",
  "vattenkastanjer": "fruit & vegetables",
  "vattenmelon": "fruit & vegetables",
  "veal": "meat and fish",
  "vegetable broth": "pantry",
  "vegetable stock": "pantry",
  "venison": "meat and fish",
  "vetemjöl": "pantry",
  "vildris": "pantry",
  "viltkött": "meat and fish",
  "vindruva": "fruit & vegetables",
  "vindruvor": "fruit & vegetables",
  "vinegar": "pantry",
  "vinäger": "pantry",
  "vispgrädde": "dairy",
  "vit choklad": "pantry",
  "vita bönor": "pantry",
  "vitkål": "fruit & vegetables",
  "vitlök": "fruit & vegetables",
  "vitpeppar": "pantry",
  "vitt bröd": "pantry",
  "vårrulleark": "pantry",
  "wakame": "pantry",
  "walnut": "pantry",
  "walnuts": "pantry",
  "wasabi": "pantry",
  "water chestnuts": "fruit & vegetables",
  "watermelon": "fruit & vegetables",
  "wheat flour": "pantry",
  "white beans": "pantry",
  "white bread": "pantry",
  "white cabbage": "fruit & vegetables",
  "white chocolate": "pantry",
  "white pepper": "pantry",
  "white vinegar": "pantry",
  "whole milk": "dairy",
  "wholegrain bread": "pantry",
  "wild rice": "pantry",
  "worcestershire sauce": "pantry",
  "yeast": "pantry",
  "yellow curry paste": "pantry",
  "yellow onion": "fruit & vegetables",
  "yellow onions": "fruit & vegetables",
  "yellow peas": "pantry",
  "yoghurt": "dairy",
  "yoghurtar": "dairy",
  "yoghurts": "dairy",
  "yogurt": "dairy",
  "yogurts": "dairy",
  "zaatar": "pantry",
  "zander": "meat and fish",
  "zucchini": "fruit & vegetables",
  "ädelost": "dairy",
  "ägg": "dairy",
  "äggnudel": "pantry",
  "äggnudlar": "pantry",
  "äggula": "dairy",
  "äggulor": "dairy",
  "äggvita": "dairy",
  "äggvitor": "dairy",
  "älgkött": "meat and fish",
  "äppelcidervinäger": "pantry",
  "äpple": "fruit & vegetables",
  "äpplen": "fruit & vegetables",
  "ärtor": "fruit & vegetables",
  "ättika": "pantry",
  "ättiksgurka": "pantry",
  "öring": "meat and fish"
}
